rdlab_dataset/__init__.py
rdlab_dataset/module.py
rdlab_dataset/background/background_01.jpg
rdlab_dataset/background/background_02.jpg
rdlab_dataset/background/background_03.jpg
rdlab_dataset/background/background_04.jpg
rdlab_dataset/background/background_05.jpg
rdlab_dataset/background/background_06.jpg
rdlab_dataset/background/background_07.jpg
rdlab_dataset/background/background_08.jpg
rdlab_dataset/background/background_09.jpg
rdlab_dataset/background/background_10.jpg
rdlab_dataset/data/address_kh_data.pkl
rdlab_dataset/data/combined_khmer_english.pkl
rdlab_dataset/data/khmer_location_combinations.pkl
rdlab_dataset/data/wild_khmer_data.pkl
rdlab_dataset/data/wild_khmer_sentences.pkl
rdlab_dataset/font/AKbalthom_KhmerHand.ttf
rdlab_dataset/font/Kh_MPS_Fasthand.ttf
rdlab_dataset/font/Kh_Writhand.ttf
rdlab_dataset-0.4.4.dist-info/METADATA
rdlab_dataset-0.4.4.dist-info/WHEEL
rdlab_dataset-0.4.4.dist-info/top_level.txt
rdlab_dataset-0.4.4.dist-info/RECORD
