Metadata-Version: 2.4
Name: rdlab_dataset
Version: 0.4.4
Home-page: https://github.com/SoyVitouPro/rdlab_dataset
Author: soyvitou
Author-email: soyvitoupro@gmail.com
Classifier: Programming Language :: Python :: 3
Classifier: License :: OSI Approved :: MIT License
Classifier: Operating System :: OS Independent
Requires-Python: >=3.6
Requires-Dist: matplotlib
Requires-Dist: Pillow
Requires-Dist: numpy
Dynamic: author
Dynamic: author-email
Dynamic: classifier
Dynamic: description
Dynamic: description-content-type
Dynamic: home-page
Dynamic: requires-dist
Dynamic: requires-python
